odoo/addons/contract_payment_auto/README.rst
odoo/addons/contract_payment_auto/__init__.py
odoo/addons/contract_payment_auto/__manifest__.py
odoo/addons/contract_payment_auto/data/ir_cron_data.xml
odoo/addons/contract_payment_auto/data/mail_template_data.xml
odoo/addons/contract_payment_auto/i18n/ca.po
odoo/addons/contract_payment_auto/i18n/contract_payment_auto.pot
odoo/addons/contract_payment_auto/i18n/de.po
odoo/addons/contract_payment_auto/i18n/el_GR.po
odoo/addons/contract_payment_auto/i18n/es.po
odoo/addons/contract_payment_auto/i18n/es_MX.po
odoo/addons/contract_payment_auto/i18n/fi.po
odoo/addons/contract_payment_auto/i18n/fr.po
odoo/addons/contract_payment_auto/i18n/gl.po
odoo/addons/contract_payment_auto/i18n/hi_IN.po
odoo/addons/contract_payment_auto/i18n/hr.po
odoo/addons/contract_payment_auto/i18n/hr_HR.po
odoo/addons/contract_payment_auto/i18n/hu.po
odoo/addons/contract_payment_auto/i18n/it.po
odoo/addons/contract_payment_auto/i18n/nl.po
odoo/addons/contract_payment_auto/i18n/nl_NL.po
odoo/addons/contract_payment_auto/i18n/pt.po
odoo/addons/contract_payment_auto/i18n/pt_BR.po
odoo/addons/contract_payment_auto/i18n/pt_PT.po
odoo/addons/contract_payment_auto/i18n/ro.po
odoo/addons/contract_payment_auto/i18n/ru.po
odoo/addons/contract_payment_auto/i18n/sk_SK.po
odoo/addons/contract_payment_auto/i18n/sl.po
odoo/addons/contract_payment_auto/i18n/tr.po
odoo/addons/contract_payment_auto/i18n/tr_TR.po
odoo/addons/contract_payment_auto/i18n/zh_CN.po
odoo/addons/contract_payment_auto/models/__init__.py
odoo/addons/contract_payment_auto/models/abstract_contract.py
odoo/addons/contract_payment_auto/models/account_move.py
odoo/addons/contract_payment_auto/models/contract.py
odoo/addons/contract_payment_auto/models/res_partner.py
odoo/addons/contract_payment_auto/readme/CONTRIBUTORS.rst
odoo/addons/contract_payment_auto/readme/USAGE.rst
odoo/addons/contract_payment_auto/static/description/icon.png
odoo/addons/contract_payment_auto/tests/__init__.py
odoo_addon_contract_payment_auto-16.0.1.0.0.6.dist-info/METADATA
odoo_addon_contract_payment_auto-16.0.1.0.0.6.dist-info/WHEEL
odoo_addon_contract_payment_auto-16.0.1.0.0.6.dist-info/top_level.txt
odoo_addon_contract_payment_auto-16.0.1.0.0.6.dist-info/RECORD
