Metadata-Version: 2.1
Name: odoo-addon-contract_payment_auto
Version: 16.0.1.0.0.6
Summary: Adds automatic payments to contracts.
Home-page: https://github.com/OCA/contract
Author: LasLabs, Odoo Community Association (OCA)
Author-email: support@odoo-community.org
License: AGPL-3
Classifier: Programming Language :: Python
Classifier: Framework :: Odoo
Classifier: Framework :: Odoo :: 16.0
Classifier: License :: OSI Approved :: GNU Affero General Public License v3
Requires-Python: >=3.10
Requires-Dist: odoo-addon-contract<16.1dev,>=16.0dev
Requires-Dist: odoo<16.1dev,>=16.0a
